Boost-stubs/Python.pyi
Boost-stubs/__init__.pyi
Boost-stubs/py.typed
pxr-stubs/Ar/__init__.pyi
pxr-stubs/CameraUtil/__init__.pyi
pxr-stubs/Garch/__init__.pyi
pxr-stubs/GeomUtil/__init__.pyi
pxr-stubs/Gf/__init__.pyi
pxr-stubs/Glf/__init__.pyi
pxr-stubs/Kind/__init__.pyi
pxr-stubs/Ndr/__init__.pyi
pxr-stubs/Pcp/__init__.pyi
pxr-stubs/Plug/__init__.pyi
pxr-stubs/PxOsd/__init__.pyi
pxr-stubs/Sdf/__init__.pyi
pxr-stubs/Sdr/__init__.pyi
pxr-stubs/Sdr/shaderParserTestUtils.pyi
pxr-stubs/SdrGlslfx/__init__.pyi
pxr-stubs/Tf/__init__.pyi
pxr-stubs/Trace/__init__.pyi
pxr-stubs/Ts/TsTest_Comparator.pyi
pxr-stubs/Ts/TsTest_CompareBaseline.pyi
pxr-stubs/Ts/TsTest_Grapher.pyi
pxr-stubs/Ts/__init__.pyi
pxr-stubs/Usd/__init__.pyi
pxr-stubs/UsdAppUtils/__init__.pyi
pxr-stubs/UsdAppUtils/cameraArgs.pyi
pxr-stubs/UsdAppUtils/colorArgs.pyi
pxr-stubs/UsdAppUtils/complexityArgs.pyi
pxr-stubs/UsdAppUtils/framesArgs.pyi
pxr-stubs/UsdAppUtils/rendererArgs.pyi
pxr-stubs/UsdBakeMtlx/__init__.pyi
pxr-stubs/UsdGeom/__init__.pyi
pxr-stubs/UsdHydra/__init__.pyi
pxr-stubs/UsdImagingGL/__init__.pyi
pxr-stubs/UsdLux/__init__.pyi
pxr-stubs/UsdMedia/__init__.pyi
pxr-stubs/UsdMtlx/__init__.pyi
pxr-stubs/UsdPhysics/__init__.pyi
pxr-stubs/UsdProc/__init__.pyi
pxr-stubs/UsdRender/__init__.pyi
pxr-stubs/UsdResolverExample/__init__.pyi
pxr-stubs/UsdRi/__init__.pyi
pxr-stubs/UsdSchemaExamples/__init__.pyi
pxr-stubs/UsdShade/__init__.pyi
pxr-stubs/UsdShaders/__init__.pyi
pxr-stubs/UsdSkel/__init__.pyi
pxr-stubs/UsdUI/__init__.pyi
pxr-stubs/UsdUtils/__init__.pyi
pxr-stubs/UsdUtils/complianceChecker.pyi
pxr-stubs/UsdUtils/constantsGroup.pyi
pxr-stubs/UsdUtils/fixBrokenPixarSchemas.pyi
pxr-stubs/UsdUtils/toolPaths.pyi
pxr-stubs/UsdUtils/updateSchemaWithSdrNode.pyi
pxr-stubs/UsdUtils/usdzUtils.pyi
pxr-stubs/UsdVol/__init__.pyi
pxr-stubs/Usdviewq/__init__.pyi
pxr-stubs/Usdviewq/adjustDefaultMaterial.pyi
pxr-stubs/Usdviewq/adjustDefaultMaterialUI.pyi
pxr-stubs/Usdviewq/adjustFreeCamera.pyi
types_usd-24.5.1.dist-info/METADATA
types_usd-24.5.1.dist-info/WHEEL
types_usd-24.5.1.dist-info/RECORD
